{
    "groupSize": 7,
    "groups": [
        {
            "dx": 417.9849738253356,
            "dy": 186.03539569461594,
            "name": 0,
            "x": 0.0,
            "y": 0.0
        },
        {
            "dx": 345.918599027864,
            "dy": 186.03539569461594,
            "name": 1,
            "x": 297.65663311138553,
            "y": 413.964604305384
        },
        {
            "dx": 297.65663311138553,
            "dy": 243.22401494146683,
            "name": 2,
            "x": 0.0,
            "y": 276.1183641914555
        },
        {
            "dx": 364.68673377722894,
            "dy": 227.9292086107681,
            "name": 3,
            "x": 297.65663311138553,
            "y": 186.03539569461594
        },
        {
            "dx": 297.65663311138553,
            "dy": 162.14934329431122,
            "name": 4,
            "x": 662.3433668886146,
            "y": 186.03539569461597
        },
        {
            "dx": 504.46462358230156,
            "dy": 186.03539569461594,
            "name": 5,
            "x": 417.9849738253356,
            "y": 0.0
        },
        {
            "dx": 297.65663311138553,
            "dy": 90.08296849683958,
            "name": 6,
            "x": 0.0,
            "y": 186.03539569461594
        },
        {
            "dx": 960,
            "dy": 600,
            "x": 0,
            "y": 0
        }
    ],
    "layout": "Chaturvedi",
    "level": "low",
    "linkMax": 5,
    "linkMin": 6,
    "linkOutMost": [
        1
    ],
    "linkSize": 261,
    "links": [
        {
            "source": 0,
            "target": 17,
            "value": 1
        },
        {
            "source": 0,
            "target": 26,
            "value": 1
        },
        {
            "source": 0,
            "target": 38,
            "value": 1
        },
        {
            "source": 1,
            "target": 11,
            "value": 1
        },
        {
            "source": 1,
            "target": 26,
            "value": 1
        },
        {
            "source": 1,
            "target": 37,
            "value": 1
        },
        {
            "source": 2,
            "target": 11,
            "value": 1
        },
        {
            "source": 2,
            "target": 14,
            "value": 1
        },
        {
            "source": 2,
            "target": 24,
            "value": 1
        },
        {
            "source": 2,
            "target": 26,
            "value": 1
        },
        {
            "source": 3,
            "target": 15,
            "value": 1
        },
        {
            "source": 3,
            "target": 19,
            "value": 1
        },
        {
            "source": 3,
            "target": 28,
            "value": 1
        },
        {
            "source": 4,
            "target": 5,
            "value": 1
        },
        {
            "source": 4,
            "target": 12,
            "value": 1
        },
        {
            "source": 4,
            "target": 20,
            "value": 1
        },
        {
            "source": 4,
            "target": 24,
            "value": 1
        },
        {
            "source": 4,
            "target": 27,
            "value": 1
        },
        {
            "source": 4,
            "target": 28,
            "value": 1
        },
        {
            "source": 4,
            "target": 38,
            "value": 1
        },
        {
            "source": 5,
            "target": 20,
            "value": 1
        },
        {
            "source": 6,
            "target": 7,
            "value": 1
        },
        {
            "source": 7,
            "target": 18,
            "value": 1
        },
        {
            "source": 7,
            "target": 42,
            "value": 1
        },
        {
            "source": 9,
            "target": 10,
            "value": 1
        },
        {
            "source": 9,
            "target": 11,
            "value": 1
        },
        {
            "source": 9,
            "target": 13,
            "value": 1
        },
        {
            "source": 9,
            "target": 20,
            "value": 1
        },
        {
            "source": 9,
            "target": 25,
            "value": 1
        },
        {
            "source": 9,
            "target": 27,
            "value": 1
        },
        {
            "source": 9,
            "target": 38,
            "value": 1
        },
        {
            "source": 10,
            "target": 28,
            "value": 1
        },
        {
            "source": 12,
            "target": 35,
            "value": 1
        },
        {
            "source": 13,
            "target": 14,
            "value": 1
        },
        {
            "source": 13,
            "target": 19,
            "value": 1
        },
        {
            "source": 13,
            "target": 23,
            "value": 1
        },
        {
            "source": 13,
            "target": 26,
            "value": 1
        },
        {
            "source": 14,
            "target": 45,
            "value": 1
        },
        {
            "source": 15,
            "target": 40,
            "value": 1
        },
        {
            "source": 17,
            "target": 49,
            "value": 1
        },
        {
            "source": 18,
            "target": 28,
            "value": 1
        },
        {
            "source": 19,
            "target": 20,
            "value": 1
        },
        {
            "source": 21,
            "target": 27,
            "value": 1
        },
        {
            "source": 22,
            "target": 23,
            "value": 1
        },
        {
            "source": 22,
            "target": 27,
            "value": 1
        },
        {
            "source": 23,
            "target": 28,
            "value": 1
        },
        {
            "source": 23,
            "target": 29,
            "value": 1
        },
        {
            "source": 24,
            "target": 29,
            "value": 1
        },
        {
            "source": 24,
            "target": 39,
            "value": 1
        },
        {
            "source": 27,
            "target": 50,
            "value": 1
        },
        {
            "source": 29,
            "target": 32,
            "value": 1
        },
        {
            "source": 29,
            "target": 38,
            "value": 1
        },
        {
            "source": 29,
            "target": 42,
            "value": 1
        },
        {
            "source": 29,
            "target": 46,
            "value": 1
        },
        {
            "source": 29,
            "target": 65,
            "value": 1
        },
        {
            "source": 29,
            "target": 92,
            "value": 1
        },
        {
            "source": 30,
            "target": 32,
            "value": 1
        },
        {
            "source": 30,
            "target": 83,
            "value": 1
        },
        {
            "source": 31,
            "target": 33,
            "value": 1
        },
        {
            "source": 31,
            "target": 37,
            "value": 1
        },
        {
            "source": 33,
            "target": 43,
            "value": 1
        },
        {
            "source": 34,
            "target": 44,
            "value": 1
        },
        {
            "source": 34,
            "target": 46,
            "value": 1
        },
        {
            "source": 35,
            "target": 41,
            "value": 1
        },
        {
            "source": 35,
            "target": 44,
            "value": 1
        },
        {
            "source": 35,
            "target": 73,
            "value": 1
        },
        {
            "source": 36,
            "target": 40,
            "value": 1
        },
        {
            "source": 36,
            "target": 50,
            "value": 1
        },
        {
            "source": 36,
            "target": 52,
            "value": 1
        },
        {
            "source": 37,
            "target": 82,
            "value": 1
        },
        {
            "source": 37,
            "target": 105,
            "value": 1
        },
        {
            "source": 38,
            "target": 82,
            "value": 1
        },
        {
            "source": 38,
            "target": 105,
            "value": 1
        },
        {
            "source": 40,
            "target": 42,
            "value": 1
        },
        {
            "source": 40,
            "target": 52,
            "value": 1
        },
        {
            "source": 41,
            "target": 48,
            "value": 1
        },
        {
            "source": 42,
            "target": 48,
            "value": 1
        },
        {
            "source": 42,
            "target": 51,
            "value": 1
        },
        {
            "source": 44,
            "target": 59,
            "value": 1
        },
        {
            "source": 44,
            "target": 63,
            "value": 1
        },
        {
            "source": 45,
            "target": 46,
            "value": 1
        },
        {
            "source": 46,
            "target": 52,
            "value": 1
        },
        {
            "source": 48,
            "target": 99,
            "value": 1
        },
        {
            "source": 50,
            "target": 100,
            "value": 1
        },
        {
            "source": 52,
            "target": 55,
            "value": 1
        },
        {
            "source": 53,
            "target": 68,
            "value": 1
        },
        {
            "source": 54,
            "target": 147,
            "value": 1
        },
        {
            "source": 55,
            "target": 61,
            "value": 1
        },
        {
            "source": 55,
            "target": 73,
            "value": 1
        },
        {
            "source": 56,
            "target": 63,
            "value": 1
        },
        {
            "source": 56,
            "target": 67,
            "value": 1
        },
        {
            "source": 56,
            "target": 154,
            "value": 1
        },
        {
            "source": 57,
            "target": 74,
            "value": 1
        },
        {
            "source": 57,
            "target": 142,
            "value": 1
        },
        {
            "source": 58,
            "target": 61,
            "value": 1
        },
        {
            "source": 58,
            "target": 139,
            "value": 1
        },
        {
            "source": 59,
            "target": 76,
            "value": 1
        },
        {
            "source": 59,
            "target": 134,
            "value": 1
        },
        {
            "source": 60,
            "target": 62,
            "value": 1
        },
        {
            "source": 60,
            "target": 63,
            "value": 1
        },
        {
            "source": 60,
            "target": 67,
            "value": 1
        },
        {
            "source": 60,
            "target": 71,
            "value": 1
        },
        {
            "source": 60,
            "target": 75,
            "value": 1
        },
        {
            "source": 60,
            "target": 77,
            "value": 1
        },
        {
            "source": 60,
            "target": 149,
            "value": 1
        },
        {
            "source": 61,
            "target": 74,
            "value": 1
        },
        {
            "source": 61,
            "target": 141,
            "value": 1
        },
        {
            "source": 62,
            "target": 139,
            "value": 1
        },
        {
            "source": 63,
            "target": 71,
            "value": 1
        },
        {
            "source": 63,
            "target": 161,
            "value": 1
        },
        {
            "source": 65,
            "target": 67,
            "value": 1
        },
        {
            "source": 65,
            "target": 137,
            "value": 1
        },
        {
            "source": 67,
            "target": 69,
            "value": 1
        },
        {
            "source": 67,
            "target": 159,
            "value": 1
        },
        {
            "source": 68,
            "target": 72,
            "value": 1
        },
        {
            "source": 69,
            "target": 71,
            "value": 1
        },
        {
            "source": 69,
            "target": 74,
            "value": 1
        },
        {
            "source": 70,
            "target": 73,
            "value": 1
        },
        {
            "source": 70,
            "target": 146,
            "value": 1
        },
        {
            "source": 72,
            "target": 143,
            "value": 1
        },
        {
            "source": 72,
            "target": 155,
            "value": 1
        },
        {
            "source": 74,
            "target": 158,
            "value": 1
        },
        {
            "source": 75,
            "target": 135,
            "value": 1
        },
        {
            "source": 76,
            "target": 133,
            "value": 1
        },
        {
            "source": 80,
            "target": 81,
            "value": 1
        },
        {
            "source": 80,
            "target": 86,
            "value": 1
        },
        {
            "source": 80,
            "target": 103,
            "value": 1
        },
        {
            "source": 80,
            "target": 105,
            "value": 1
        },
        {
            "source": 81,
            "target": 99,
            "value": 1
        },
        {
            "source": 81,
            "target": 170,
            "value": 1
        },
        {
            "source": 82,
            "target": 89,
            "value": 1
        },
        {
            "source": 83,
            "target": 85,
            "value": 1
        },
        {
            "source": 83,
            "target": 89,
            "value": 1
        },
        {
            "source": 83,
            "target": 93,
            "value": 1
        },
        {
            "source": 83,
            "target": 106,
            "value": 1
        },
        {
            "source": 83,
            "target": 166,
            "value": 1
        },
        {
            "source": 84,
            "target": 87,
            "value": 1
        },
        {
            "source": 84,
            "target": 91,
            "value": 1
        },
        {
            "source": 85,
            "target": 96,
            "value": 1
        },
        {
            "source": 85,
            "target": 98,
            "value": 1
        },
        {
            "source": 85,
            "target": 165,
            "value": 1
        },
        {
            "source": 86,
            "target": 90,
            "value": 1
        },
        {
            "source": 86,
            "target": 93,
            "value": 1
        },
        {
            "source": 86,
            "target": 94,
            "value": 1
        },
        {
            "source": 86,
            "target": 97,
            "value": 1
        },
        {
            "source": 87,
            "target": 88,
            "value": 1
        },
        {
            "source": 87,
            "target": 89,
            "value": 1
        },
        {
            "source": 87,
            "target": 102,
            "value": 1
        },
        {
            "source": 88,
            "target": 110,
            "value": 1
        },
        {
            "source": 88,
            "target": 172,
            "value": 1
        },
        {
            "source": 89,
            "target": 100,
            "value": 1
        },
        {
            "source": 89,
            "target": 109,
            "value": 1
        },
        {
            "source": 89,
            "target": 110,
            "value": 1
        },
        {
            "source": 90,
            "target": 173,
            "value": 1
        },
        {
            "source": 91,
            "target": 97,
            "value": 1
        },
        {
            "source": 91,
            "target": 100,
            "value": 1
        },
        {
            "source": 91,
            "target": 110,
            "value": 1
        },
        {
            "source": 92,
            "target": 99,
            "value": 1
        },
        {
            "source": 92,
            "target": 106,
            "value": 1
        },
        {
            "source": 92,
            "target": 109,
            "value": 1
        },
        {
            "source": 93,
            "target": 99,
            "value": 1
        },
        {
            "source": 93,
            "target": 106,
            "value": 1
        },
        {
            "source": 93,
            "target": 109,
            "value": 1
        },
        {
            "source": 94,
            "target": 106,
            "value": 1
        },
        {
            "source": 95,
            "target": 99,
            "value": 1
        },
        {
            "source": 95,
            "target": 100,
            "value": 1
        },
        {
            "source": 95,
            "target": 105,
            "value": 1
        },
        {
            "source": 95,
            "target": 108,
            "value": 1
        },
        {
            "source": 96,
            "target": 99,
            "value": 1
        },
        {
            "source": 96,
            "target": 104,
            "value": 1
        },
        {
            "source": 96,
            "target": 105,
            "value": 1
        },
        {
            "source": 98,
            "target": 107,
            "value": 1
        },
        {
            "source": 99,
            "target": 103,
            "value": 1
        },
        {
            "source": 103,
            "target": 106,
            "value": 1
        },
        {
            "source": 113,
            "target": 123,
            "value": 1
        },
        {
            "source": 114,
            "target": 124,
            "value": 1
        },
        {
            "source": 115,
            "target": 126,
            "value": 1
        },
        {
            "source": 117,
            "target": 120,
            "value": 1
        },
        {
            "source": 117,
            "target": 124,
            "value": 1
        },
        {
            "source": 118,
            "target": 119,
            "value": 1
        },
        {
            "source": 118,
            "target": 121,
            "value": 1
        },
        {
            "source": 119,
            "target": 124,
            "value": 1
        },
        {
            "source": 120,
            "target": 126,
            "value": 1
        },
        {
            "source": 120,
            "target": 127,
            "value": 1
        },
        {
            "source": 121,
            "target": 122,
            "value": 1
        },
        {
            "source": 122,
            "target": 123,
            "value": 1
        },
        {
            "source": 124,
            "target": 128,
            "value": 1
        },
        {
            "source": 129,
            "target": 139,
            "value": 1
        },
        {
            "source": 129,
            "target": 145,
            "value": 1
        },
        {
            "source": 129,
            "target": 153,
            "value": 1
        },
        {
            "source": 129,
            "target": 155,
            "value": 1
        },
        {
            "source": 130,
            "target": 136,
            "value": 1
        },
        {
            "source": 130,
            "target": 137,
            "value": 1
        },
        {
            "source": 130,
            "target": 150,
            "value": 1
        },
        {
            "source": 130,
            "target": 152,
            "value": 1
        },
        {
            "source": 130,
            "target": 156,
            "value": 1
        },
        {
            "source": 131,
            "target": 133,
            "value": 1
        },
        {
            "source": 131,
            "target": 134,
            "value": 1
        },
        {
            "source": 131,
            "target": 149,
            "value": 1
        },
        {
            "source": 132,
            "target": 135,
            "value": 1
        },
        {
            "source": 132,
            "target": 140,
            "value": 1
        },
        {
            "source": 132,
            "target": 147,
            "value": 1
        },
        {
            "source": 132,
            "target": 151,
            "value": 1
        },
        {
            "source": 133,
            "target": 137,
            "value": 1
        },
        {
            "source": 133,
            "target": 149,
            "value": 1
        },
        {
            "source": 133,
            "target": 162,
            "value": 1
        },
        {
            "source": 133,
            "target": 163,
            "value": 1
        },
        {
            "source": 134,
            "target": 136,
            "value": 1
        },
        {
            "source": 135,
            "target": 146,
            "value": 1
        },
        {
            "source": 135,
            "target": 151,
            "value": 1
        },
        {
            "source": 136,
            "target": 158,
            "value": 1
        },
        {
            "source": 136,
            "target": 161,
            "value": 1
        },
        {
            "source": 137,
            "target": 144,
            "value": 1
        },
        {
            "source": 138,
            "target": 140,
            "value": 1
        },
        {
            "source": 138,
            "target": 142,
            "value": 1
        },
        {
            "source": 138,
            "target": 146,
            "value": 1
        },
        {
            "source": 138,
            "target": 163,
            "value": 1
        },
        {
            "source": 139,
            "target": 157,
            "value": 1
        },
        {
            "source": 140,
            "target": 141,
            "value": 1
        },
        {
            "source": 140,
            "target": 150,
            "value": 1
        },
        {
            "source": 140,
            "target": 157,
            "value": 1
        },
        {
            "source": 140,
            "target": 158,
            "value": 1
        },
        {
            "source": 140,
            "target": 159,
            "value": 1
        },
        {
            "source": 141,
            "target": 157,
            "value": 1
        },
        {
            "source": 142,
            "target": 159,
            "value": 1
        },
        {
            "source": 143,
            "target": 151,
            "value": 1
        },
        {
            "source": 143,
            "target": 153,
            "value": 1
        },
        {
            "source": 143,
            "target": 157,
            "value": 1
        },
        {
            "source": 143,
            "target": 158,
            "value": 1
        },
        {
            "source": 144,
            "target": 147,
            "value": 1
        },
        {
            "source": 144,
            "target": 156,
            "value": 1
        },
        {
            "source": 146,
            "target": 155,
            "value": 1
        },
        {
            "source": 147,
            "target": 152,
            "value": 1
        },
        {
            "source": 147,
            "target": 161,
            "value": 1
        },
        {
            "source": 147,
            "target": 162,
            "value": 1
        },
        {
            "source": 148,
            "target": 149,
            "value": 1
        },
        {
            "source": 148,
            "target": 162,
            "value": 1
        },
        {
            "source": 149,
            "target": 155,
            "value": 1
        },
        {
            "source": 149,
            "target": 159,
            "value": 1
        },
        {
            "source": 149,
            "target": 160,
            "value": 1
        },
        {
            "source": 151,
            "target": 154,
            "value": 1
        },
        {
            "source": 151,
            "target": 155,
            "value": 1
        },
        {
            "source": 151,
            "target": 160,
            "value": 1
        },
        {
            "source": 156,
            "target": 163,
            "value": 1
        },
        {
            "source": 164,
            "target": 168,
            "value": 1
        },
        {
            "source": 165,
            "target": 168,
            "value": 1
        },
        {
            "source": 166,
            "target": 168,
            "value": 1
        },
        {
            "source": 168,
            "target": 172,
            "value": 1
        },
        {
            "source": 170,
            "target": 173,
            "value": 1
        },
        {
            "source": 0,
            "target": 83,
            "value": 1
        },
        {
            "source": 4,
            "target": 151,
            "value": 1
        },
        {
            "source": 9,
            "target": 171,
            "value": 1
        },
        {
            "source": 18,
            "target": 102,
            "value": 1
        },
        {
            "source": 19,
            "target": 106,
            "value": 1
        },
        {
            "source": 21,
            "target": 134,
            "value": 1
        },
        {
            "source": 44,
            "target": 168,
            "value": 1
        },
        {
            "source": 53,
            "target": 80,
            "value": 1
        },
        {
            "source": 85,
            "target": 89,
            "value": 1
        },
        {
            "source": 88,
            "target": 97,
            "value": 1
        },
        {
            "source": 138,
            "target": 172,
            "value": 1
        },
        {
            "source": 142,
            "target": 170,
            "value": 1
        }
    ],
    "mostConnected": [
        [
            2,
            5
        ]
    ],
    "nodeMax": 5,
    "nodeMin": 6,
    "nodeSize": 174,
    "nodes": [
        {
            "cx": 221.73067,
            "cy": 109.79559,
            "group": 0,
            "name": 0
        },
        {
            "cx": 196.749,
            "cy": 112.25352,
            "group": 0,
            "name": 1
        },
        {
            "cx": 202.19377,
            "cy": 63.74459,
            "group": 0,
            "name": 2
        },
        {
            "cx": 229.66623,
            "cy": 98.53005,
            "group": 0,
            "name": 3
        },
        {
            "cx": 221.16772,
            "cy": 89.317665,
            "group": 0,
            "name": 4
        },
        {
            "cx": 253.16814,
            "cy": 53.982857,
            "group": 0,
            "name": 5
        },
        {
            "cx": 200.03967,
            "cy": 134.46118,
            "group": 0,
            "name": 6
        },
        {
            "cx": 195.32762,
            "cy": 54.194977,
            "group": 0,
            "name": 7
        },
        {
            "cx": 202.67876,
            "cy": 101.23212,
            "group": 0,
            "name": 8
        },
        {
            "cx": 222.23035,
            "cy": 123.26453,
            "group": 0,
            "name": 9
        },
        {
            "cx": 233.26314,
            "cy": 60.185707,
            "group": 0,
            "name": 10
        },
        {
            "cx": 264.28162,
            "cy": 94.69373,
            "group": 0,
            "name": 11
        },
        {
            "cx": 163.65483,
            "cy": 87.96123,
            "group": 0,
            "name": 12
        },
        {
            "cx": 216.92331,
            "cy": 76.673355,
            "group": 0,
            "name": 13
        },
        {
            "cx": 178.25224,
            "cy": 112.47066,
            "group": 0,
            "name": 14
        },
        {
            "cx": 196.43854,
            "cy": 76.49223,
            "group": 0,
            "name": 15
        },
        {
            "cx": 240.66367,
            "cy": 107.64375,
            "group": 0,
            "name": 16
        },
        {
            "cx": 172.90714,
            "cy": 95.13823,
            "group": 0,
            "name": 17
        },
        {
            "cx": 234.86967,
            "cy": 84.37822,
            "group": 0,
            "name": 18
        },
        {
            "cx": 217.4351,
            "cy": 139.05504,
            "group": 0,
            "name": 19
        },
        {
            "cx": 174.02914,
            "cy": 74.89748,
            "group": 0,
            "name": 20
        },
        {
            "cx": 248.99707,
            "cy": 91.00843,
            "group": 0,
            "name": 21
        },
        {
            "cx": 196.88155,
            "cy": 89.07962,
            "group": 0,
            "name": 22
        },
        {
            "cx": 224.8814,
            "cy": 49.337868,
            "group": 0,
            "name": 23
        },
        {
            "cx": 241.27539,
            "cy": 129.68225,
            "group": 0,
            "name": 24
        },
        {
            "cx": 160.31409,
            "cy": 64.74443,
            "group": 0,
            "name": 25
        },
        {
            "cx": 253.53398,
            "cy": 76.12861,
            "group": 0,
            "name": 26
        },
        {
            "cx": 177.27359,
            "cy": 130.87715,
            "group": 0,
            "name": 27
        },
        {
            "cx": 171.47073,
            "cy": 54.81784,
            "group": 0,
            "name": 28
        },
        {
            "cx": 451.69067,
            "cy": 517.72107,
            "group": 1,
            "name": 29
        },
        {
            "cx": 498.18427,
            "cy": 523.7501,
            "group": 1,
            "name": 30
        },
        {
            "cx": 423.53436,
            "cy": 514.80237,
            "group": 1,
            "name": 31
        },
        {
            "cx": 486.60098,
            "cy": 456.37094,
            "group": 1,
            "name": 32
        },
        {
            "cx": 497.1336,
            "cy": 490.3797,
            "group": 1,
            "name": 33
        },
        {
            "cx": 517.81976,
            "cy": 522.9878,
            "group": 1,
            "name": 34
        },
        {
            "cx": 485.41266,
            "cy": 514.00867,
            "group": 1,
            "name": 35
        },
        {
            "cx": 461.73267,
            "cy": 488.49823,
            "group": 1,
            "name": 36
        },
        {
            "cx": 480.30283,
            "cy": 519.71643,
            "group": 1,
            "name": 37
        },
        {
            "cx": 480.60507,
            "cy": 498.4312,
            "group": 1,
            "name": 38
        },
        {
            "cx": 466.6328,
            "cy": 513.183,
            "group": 1,
            "name": 39
        },
        {
            "cx": 456.06137,
            "cy": 540.0244,
            "group": 1,
            "name": 40
        },
        {
            "cx": 441.85074,
            "cy": 470.4709,
            "group": 1,
            "name": 41
        },
        {
            "cx": 516.6528,
            "cy": 490.8249,
            "group": 1,
            "name": 42
        },
        {
            "cx": 443.75186,
            "cy": 550.0887,
            "group": 1,
            "name": 43
        },
        {
            "cx": 462.85953,
            "cy": 470.07852,
            "group": 1,
            "name": 44
        },
        {
            "cx": 484.35248,
            "cy": 531.5707,
            "group": 1,
            "name": 45
        },
        {
            "cx": 432.53998,
            "cy": 491.22037,
            "group": 1,
            "name": 46
        },
        {
            "cx": 494.18033,
            "cy": 503.5058,
            "group": 1,
            "name": 47
        },
        {
            "cx": 469.454,
            "cy": 539.08905,
            "group": 1,
            "name": 48
        },
        {
            "cx": 450.03525,
            "cy": 500.51227,
            "group": 1,
            "name": 49
        },
        {
            "cx": 494.24814,
            "cy": 538.51636,
            "group": 1,
            "name": 50
        },
        {
            "cx": 435.5844,
            "cy": 527.244,
            "group": 1,
            "name": 51
        },
        {
            "cx": 499.517,
            "cy": 474.2168,
            "group": 1,
            "name": 52
        },
        {
            "cx": 132.35243,
            "cy": 363.0261,
            "group": 2,
            "name": 53
        },
        {
            "cx": 143.7212,
            "cy": 413.78363,
            "group": 2,
            "name": 54
        },
        {
            "cx": 119.91368,
            "cy": 401.51526,
            "group": 2,
            "name": 55
        },
        {
            "cx": 184.19493,
            "cy": 369.93744,
            "group": 2,
            "name": 56
        },
        {
            "cx": 170.10947,
            "cy": 370.3661,
            "group": 2,
            "name": 57
        },
        {
            "cx": 100.93763,
            "cy": 387.33047,
            "group": 2,
            "name": 58
        },
        {
            "cx": 158.4774,
            "cy": 362.71228,
            "group": 2,
            "name": 59
        },
        {
            "cx": 162.7625,
            "cy": 392.47116,
            "group": 2,
            "name": 60
        },
        {
            "cx": 201.72653,
            "cy": 406.77344,
            "group": 2,
            "name": 61
        },
        {
            "cx": 178.32059,
            "cy": 335.89758,
            "group": 2,
            "name": 62
        },
        {
            "cx": 126.21116,
            "cy": 444.281,
            "group": 2,
            "name": 63
        },
        {
            "cx": 147.85934,
            "cy": 376.40768,
            "group": 2,
            "name": 64
        },
        {
            "cx": 187.20192,
            "cy": 392.68832,
            "group": 2,
            "name": 65
        },
        {
            "cx": 165.13358,
            "cy": 405.6002,
            "group": 2,
            "name": 66
        },
        {
            "cx": 85.02712,
            "cy": 391.5116,
            "group": 2,
            "name": 67
        },
        {
            "cx": 199.5784,
            "cy": 444.20337,
            "group": 2,
            "name": 68
        },
        {
            "cx": 169.49594,
            "cy": 443.73203,
            "group": 2,
            "name": 69
        },
        {
            "cx": 114.81474,
            "cy": 377.34756,
            "group": 2,
            "name": 70
        },
        {
            "cx": 215.85165,
            "cy": 366.92612,
            "group": 2,
            "name": 71
        },
        {
            "cx": 122.845276,
            "cy": 415.37305,
            "group": 2,
            "name": 72
        },
        {
            "cx": 198.55556,
            "cy": 362.99054,
            "group": 2,
            "name": 73
        },
        {
            "cx": 101.34555,
            "cy": 432.30817,
            "group": 2,
            "name": 74
        },
        {
            "cx": 104.54051,
            "cy": 342.8168,
            "group": 2,
            "name": 75
        },
        {
            "cx": 186.75499,
            "cy": 433.39224,
            "group": 2,
            "name": 76
        },
        {
            "cx": 69.18793,
            "cy": 427.17862,
            "group": 2,
            "name": 77
        },
        {
            "cx": 155.25583,
            "cy": 350.32605,
            "group": 2,
            "name": 78
        },
        {
            "cx": 160.2837,
            "cy": 420.7854,
            "group": 2,
            "name": 79
        },
        {
            "cx": 494.56256,
            "cy": 356.0282,
            "group": 3,
            "name": 80
        },
        {
            "cx": 457.81534,
            "cy": 304.23645,
            "group": 3,
            "name": 81
        },
        {
            "cx": 498.7779,
            "cy": 315.17682,
            "group": 3,
            "name": 82
        },
        {
            "cx": 469.6476,
            "cy": 339.11066,
            "group": 3,
            "name": 83
        },
        {
            "cx": 410.17328,
            "cy": 320.29303,
            "group": 3,
            "name": 84
        },
        {
            "cx": 525.13684,
            "cy": 293.61185,
            "group": 3,
            "name": 85
        },
        {
            "cx": 454.01904,
            "cy": 341.77383,
            "group": 3,
            "name": 86
        },
        {
            "cx": 490.17007,
            "cy": 303.76462,
            "group": 3,
            "name": 87
        },
        {
            "cx": 426.8361,
            "cy": 295.46228,
            "group": 3,
            "name": 88
        },
        {
            "cx": 436.79062,
            "cy": 278.0708,
            "group": 3,
            "name": 89
        },
        {
            "cx": 448.58505,
            "cy": 254.91743,
            "group": 3,
            "name": 90
        },
        {
            "cx": 471.17105,
            "cy": 265.0368,
            "group": 3,
            "name": 91
        },
        {
            "cx": 491.6905,
            "cy": 328.42218,
            "group": 3,
            "name": 92
        },
        {
            "cx": 494.85425,
            "cy": 291.6613,
            "group": 3,
            "name": 93
        },
        {
            "cx": 523.3316,
            "cy": 267.86057,
            "group": 3,
            "name": 94
        },
        {
            "cx": 437.8117,
            "cy": 309.4615,
            "group": 3,
            "name": 95
        },
        {
            "cx": 455.45377,
            "cy": 321.60925,
            "group": 3,
            "name": 96
        },
        {
            "cx": 543.4782,
            "cy": 310.572,
            "group": 3,
            "name": 97
        },
        {
            "cx": 427.08212,
            "cy": 327.3909,
            "group": 3,
            "name": 98
        },
        {
            "cx": 466.34967,
            "cy": 242.41977,
            "group": 3,
            "name": 99
        },
        {
            "cx": 500.17047,
            "cy": 339.2362,
            "group": 3,
            "name": 100
        },
        {
            "cx": 462.87305,
            "cy": 289.62808,
            "group": 3,
            "name": 101
        },
        {
            "cx": 542.4398,
            "cy": 276.68063,
            "group": 3,
            "name": 102
        },
        {
            "cx": 441.01108,
            "cy": 349.74432,
            "group": 3,
            "name": 103
        },
        {
            "cx": 513.4442,
            "cy": 246.28674,
            "group": 3,
            "name": 104
        },
        {
            "cx": 519.54,
            "cy": 310.2126,
            "group": 3,
            "name": 105
        },
        {
            "cx": 424.93735,
            "cy": 270.10712,
            "group": 3,
            "name": 106
        },
        {
            "cx": 506.83243,
            "cy": 275.71744,
            "group": 3,
            "name": 107
        },
        {
            "cx": 533.8757,
            "cy": 340.24176,
            "group": 3,
            "name": 108
        },
        {
            "cx": 494.19287,
            "cy": 234.63638,
            "group": 3,
            "name": 109
        },
        {
            "cx": 518.3126,
            "cy": 338.2929,
            "group": 3,
            "name": 110
        },
        {
            "cx": 797.0664,
            "cy": 266.50394,
            "group": 4,
            "name": 111
        },
        {
            "cx": 824.2332,
            "cy": 268.8769,
            "group": 4,
            "name": 112
        },
        {
            "cx": 787.61743,
            "cy": 283.67532,
            "group": 4,
            "name": 113
        },
        {
            "cx": 803.03265,
            "cy": 221.80371,
            "group": 4,
            "name": 114
        },
        {
            "cx": 790.4162,
            "cy": 252.74857,
            "group": 4,
            "name": 115
        },
        {
            "cx": 809.41077,
            "cy": 277.85223,
            "group": 4,
            "name": 116
        },
        {
            "cx": 774.2568,
            "cy": 270.99506,
            "group": 4,
            "name": 117
        },
        {
            "cx": 836.7736,
            "cy": 247.0511,
            "group": 4,
            "name": 118
        },
        {
            "cx": 783.1327,
            "cy": 239.61276,
            "group": 4,
            "name": 119
        },
        {
            "cx": 823.1636,
            "cy": 238.45036,
            "group": 4,
            "name": 120
        },
        {
            "cx": 801.82904,
            "cy": 299.2463,
            "group": 4,
            "name": 121
        },
        {
            "cx": 801.9698,
            "cy": 238.89151,
            "group": 4,
            "name": 122
        },
        {
            "cx": 850.72034,
            "cy": 268.92657,
            "group": 4,
            "name": 123
        },
        {
            "cx": 819.36786,
            "cy": 299.86954,
            "group": 4,
            "name": 124
        },
        {
            "cx": 812.48865,
            "cy": 250.67896,
            "group": 4,
            "name": 125
        },
        {
            "cx": 834.35254,
            "cy": 294.2375,
            "group": 4,
            "name": 126
        },
        {
            "cx": 778.96545,
            "cy": 294.46213,
            "group": 4,
            "name": 127
        },
        {
            "cx": 829.34796,
            "cy": 224.70248,
            "group": 4,
            "name": 128
        },
        {
            "cx": 696.9365,
            "cy": 59.881817,
            "group": 5,
            "name": 129
        },
        {
            "cx": 657.9348,
            "cy": 93.46778,
            "group": 5,
            "name": 130
        },
        {
            "cx": 659.63367,
            "cy": 125.898254,
            "group": 5,
            "name": 131
        },
        {
            "cx": 658.6616,
            "cy": 69.45212,
            "group": 5,
            "name": 132
        },
        {
            "cx": 633.65436,
            "cy": 70.59822,
            "group": 5,
            "name": 133
        },
        {
            "cx": 687.4636,
            "cy": 87.19465,
            "group": 5,
            "name": 134
        },
        {
            "cx": 682.4022,
            "cy": 121.52051,
            "group": 5,
            "name": 135
        },
        {
            "cx": 656.7198,
            "cy": 55.23678,
            "group": 5,
            "name": 136
        },
        {
            "cx": 703.5192,
            "cy": 96.39015,
            "group": 5,
            "name": 137
        },
        {
            "cx": 627.0229,
            "cy": 83.76556,
            "group": 5,
            "name": 138
        },
        {
            "cx": 662.28534,
            "cy": 83.23079,
            "group": 5,
            "name": 139
        },
        {
            "cx": 662.75226,
            "cy": 104.287155,
            "group": 5,
            "name": 140
        },
        {
            "cx": 702.6434,
            "cy": 75.285416,
            "group": 5,
            "name": 141
        },
        {
            "cx": 683.9637,
            "cy": 102.412125,
            "group": 5,
            "name": 142
        },
        {
            "cx": 678.2861,
            "cy": 83.21148,
            "group": 5,
            "name": 143
        },
        {
            "cx": 645.0103,
            "cy": 85.58792,
            "group": 5,
            "name": 144
        },
        {
            "cx": 619.81445,
            "cy": 101.39578,
            "group": 5,
            "name": 145
        },
        {
            "cx": 685.6387,
            "cy": 69.512535,
            "group": 5,
            "name": 146
        },
        {
            "cx": 715.3507,
            "cy": 105.409485,
            "group": 5,
            "name": 147
        },
        {
            "cx": 637.3688,
            "cy": 104.519615,
            "group": 5,
            "name": 148
        },
        {
            "cx": 716.30035,
            "cy": 83.292694,
            "group": 5,
            "name": 149
        },
        {
            "cx": 726.509,
            "cy": 117.49778,
            "group": 5,
            "name": 150
        },
        {
            "cx": 676.3893,
            "cy": 42.815823,
            "group": 5,
            "name": 151
        },
        {
            "cx": 663.5885,
            "cy": 155.03201,
            "group": 5,
            "name": 152
        },
        {
            "cx": 630.7572,
            "cy": 119.616066,
            "group": 5,
            "name": 153
        },
        {
            "cx": 694.86884,
            "cy": 113.02995,
            "group": 5,
            "name": 154
        },
        {
            "cx": 648.3905,
            "cy": 138.5851,
            "group": 5,
            "name": 155
        },
        {
            "cx": 638.3413,
            "cy": 51.4966,
            "group": 5,
            "name": 156
        },
        {
            "cx": 699.8381,
            "cy": 139.62532,
            "group": 5,
            "name": 157
        },
        {
            "cx": 636.8057,
            "cy": 132.3027,
            "group": 5,
            "name": 158
        },
        {
            "cx": 659.825,
            "cy": 43.504833,
            "group": 5,
            "name": 159
        },
        {
            "cx": 667.9279,
            "cy": 136.28497,
            "group": 5,
            "name": 160
        },
        {
            "cx": 652.58875,
            "cy": 112.07239,
            "group": 5,
            "name": 161
        },
        {
            "cx": 709.97815,
            "cy": 55.246784,
            "group": 5,
            "name": 162
        },
        {
            "cx": 688.61365,
            "cy": 133.22255,
            "group": 5,
            "name": 163
        },
        {
            "cx": 140.16649,
            "cy": 211.14302,
            "group": 6,
            "name": 164
        },
        {
            "cx": 154.99234,
            "cy": 223.04301,
            "group": 6,
            "name": 165
        },
        {
            "cx": 130.48145,
            "cy": 225.031,
            "group": 6,
            "name": 166
        },
        {
            "cx": 165.31656,
            "cy": 229.15771,
            "group": 6,
            "name": 167
        },
        {
            "cx": 154.03645,
            "cy": 252.88399,
            "group": 6,
            "name": 168
        },
        {
            "cx": 137.19154,
            "cy": 240.94943,
            "group": 6,
            "name": 169
        },
        {
            "cx": 155.90417,
            "cy": 211.58585,
            "group": 6,
            "name": 170
        },
        {
            "cx": 147.8991,
            "cy": 238.99619,
            "group": 6,
            "name": 171
        },
        {
            "cx": 141.36139,
            "cy": 228.80887,
            "group": 6,
            "name": 172
        },
        {
            "cx": 158.60538,
            "cy": 240.94926,
            "group": 6,
            "name": 173
        }
    ],
    "pgroup": 0.2,
    "pout": 0.0006,
    "set": 0,
    "type": "Chatu"
}